README.md
setup.py
craftplot/__init__.py
craftplot/_version.py
craftplot/aps_params.py
craftplot/colors.py
craftplot/general.py
craftplot/styles.py
craftplot.egg-info/PKG-INFO
craftplot.egg-info/SOURCES.txt
craftplot.egg-info/dependency_links.txt
craftplot.egg-info/not-zip-safe
craftplot.egg-info/requires.txt
craftplot.egg-info/top_level.txt