Metadata-Version: 2.1
Name: craftplot
Version: 0.1.1
Summary: craftplot is a python package based on mpltex for producing publication quality images for science using matplotlib.
Home-page: https://github.com/Chenghao-Wu/craftplot
Author: Zhenghao Wu
Author-email: w415146142@gmail.com
License: BSD
Platform: UNKNOWN
Classifier: Programming Language :: Python :: 3
Classifier: Intended Audience :: Science/Research
Classifier: License :: OSI Approved :: BSD License
Classifier: Operating System :: OS Independent
Classifier: Programming Language :: Python
Classifier: Topic :: Scientific/Engineering
